{
  {
    "title": "Red Bull quer resposta para desgaste de pneus “bem pior” que Ferrari na Áustria",
    "description": "Christian Horner estranhou bastante a diferença de performance entre Red Bull e Ferrari de um dia para o outro na Áustria principalmente por causa do alto desgaste de pneus do RB18",
    "image": "https://www.grandepremio.com.br/wp-content/uploads/2022/07/redbull-maxverstappen-01-6-768x432.jpg",
    "link": "https://www.grandepremio.com.br/f1/noticias/red-bull-desgaste-de-pneus-pior-ferrari-austria/"
  },
  {
    "title": "Ricciardo afasta rumores e se diz 'comprometido com a McLaren' até o fim de 2023",
    "description": "Especulações apontavam para possível substituição do australiano; nomes como Gasly e Vettel foram cotados",
    "image": "https://pubimg.band.uol.com.br/files/a97d939a0c4d071781a8.webp",
    "link": "https://www.band.uol.com.br/esportes/automobilismo/formula-1/noticias/daniel-ricciardo-contrato-mclaren-2023-16522603"
  },
  {
   "title": "Michael Masi rompe silêncio, mas evita polêmica sobre decisão da F1 em 2021",
    "description": "Em comunicado, ex-dirigente deixou claro que chegada ao cargo de diretor de provas da F1 ocorreu antes do previsto",
    "image": "https://pubimg.band.uol.com.br/files/f7f18a237e2bc48f0123.webp",
    "link": "https://www.band.uol.com.br/esportes/automobilismo/formula-1/noticias/michael-masi-declaracao-saida-f1-e-fia-16522596"
  }
}
